{
  "slide_id": 1295,
  "annotations": [
    {
      "design_deficiency_category": "Composition & Layout",
      "design_deficiency": "Poor Visual Hierarchy",
      "response": false,
      "has_strong_agreement": false
    },
    {
      "design_deficiency_category": "Composition & Layout",
      "design_deficiency": "Cluttered Layout",
      "response": true,
      "has_strong_agreement": false
    },
    {
      "design_deficiency_category": "Composition & Layout",
      "design_deficiency": "Unbalanced Space Distribution",
      "response": false,
      "has_strong_agreement": true
    },
    {
      "design_deficiency_category": "Composition & Layout",
      "design_deficiency": "Content Alignment Issues",
      "response": false,
      "has_strong_agreement": false,
      "bounding_boxes": []
    },
    {
      "design_deficiency_category": "Composition & Layout",
      "design_deficiency": "Content Overflow/Cut-off",
      "response": true,
      "has_strong_agreement": false,
      "bounding_boxes": [
        {
          "x": 908.5136332760487,
          "y": 379.220744906306,
          "width": 418.4704000422755,
          "height": 554.112529711151
        },
        {
          "x": 1298.962038162332,
          "y": 262.79191342763164,
          "width": 216.39853325592276,
          "height": 94.96627031558927
        },
        {
          "x": 965.8017063870262,
          "y": 251.89414470289188,
          "width": 177.47793374946184,
          "height": 110.53451135093178
        },
        {
          "x": 915.9833390187562,
          "y": 384.2241935033032,
          "width": 263.10325266367613,
          "height": 90.29579800498658
        },
        {
          "x": 934.6652267818574,
          "y": 465.1790468870842,
          "width": 199.27346947308,
          "height": 63.82978824490425
        },
        {
          "x": 920.6538109595315,
          "y": 746.9642096267836,
          "width": 269.33054858470973,
          "height": 110.53451135093178
        },
        {
          "x": 931.5515788213405,
          "y": 863.7260173918525,
          "width": 269.33054858470985,
          "height": 82.5116774873153
        },
        {
          "x": 503.4249842502701,
          "y": 561.7021413062077,
          "width": 175.92110976920344,
          "height": 88.73897390145237
        },
        {
          "x": 146.91229277108778,
          "y": 666.0093562430026,
          "width": 129.21639036145035,
          "height": 84.06850159084956
        },
        {
          "x": 90.866629481784,
          "y": 499.42917716483777,
          "width": 267.77372460445133,
          "height": 65.38661234843852
        },
        {
          "x": 501.86816027001163,
          "y": 496.31552895776923,
          "width": 217.95535723618133,
          "height": 65.38661234843852
        },
        {
          "x": 506.53863221078694,
          "y": 443.38350943760474,
          "width": 191.48934957178784,
          "height": 56.045667727233024
        },
        {
          "x": 550.1297036580232,
          "y": 273.6896821523714,
          "width": 160.3528699666191,
          "height": 79.39802928024676
        },
        {
          "x": 171.82147645522278,
          "y": 265.9055616347001,
          "width": 115.20497453912444,
          "height": 101.19356672972634
        },
        {
          "x": 925.3242829003068,
          "y": 496.31552895776923,
          "width": 147.89827812455155,
          "height": 57.60249183076729
        },
        {
          "x": 929.9947548410821,
          "y": 606.8500403087011,
          "width": 194.6029975323047,
          "height": 57.602491830767235
        },
        {
          "x": 919.0969869792731,
          "y": 661.3388839323998,
          "width": 175.92110976920355,
          "height": 59.15931593430162
        },
        {
          "x": 920.6538109595315,
          "y": 728.2823203843726,
          "width": 141.67098220351795,
          "height": 45.14789900249332
        },
        {
          "x": 512.7659281318207,
          "y": 648.8842911041259,
          "width": 256.8759567426423,
          "height": 51.37519541663028
        },
        {
          "x": 497.1976883292363,
          "y": 726.7254962808383,
          "width": 140.11415822325938,
          "height": 60.71614003783577
        },
        {
          "x": 98.65074938307619,
          "y": 740.7369132126466,
          "width": 227.29630111773196,
          "height": 59.1593159343015
        },
        {
          "x": 106.43486928436838,
          "y": 851.2714245635784,
          "width": 177.47793374946193,
          "height": 51.37519541663028
        },
        {
          "x": 103.3212213238515,
          "y": 907.3170922908114,
          "width": 197.71664549282167,
          "height": 51.37519541663028
        },
        {
          "x": 106.43486928436838,
          "y": 960.2491118109759,
          "width": 289.5692603280695,
          "height": 49.81837131309601
        },
        {
          "x": 98.65074938307619,
          "y": 444.94033354113895,
          "width": 104.30720667731534,
          "height": 65.38661234843858
        },
        {
          "x": 101.76439734359306,
          "y": 384.2241935033032,
          "width": 118.3186224996413,
          "height": 62.27296414137004
        },
        {
          "x": 509.65228017130386,
          "y": 384.2241935033032,
          "width": 105.86403065757378,
          "height": 57.60249183076729
        }
      ]
    },
    {
      "design_deficiency_category": "Composition & Layout",
      "design_deficiency": "Occluded Content",
      "response": false,
      "has_strong_agreement": false,
      "bounding_boxes": []
    },
    {
      "design_deficiency_category": "Typography",
      "design_deficiency": "Illegible Typeface Selection or Usage",
      "response": false,
      "has_strong_agreement": true,
      "bounding_boxes": []
    },
    {
      "design_deficiency_category": "Typography",
      "design_deficiency": "Improper Font Sizing",
      "response": false,
      "has_strong_agreement": false,
      "bounding_boxes": []
    },
    {
      "design_deficiency_category": "Typography",
      "design_deficiency": "Excessive Text Volume",
      "response": false,
      "has_strong_agreement": true
    },
    {
      "design_deficiency_category": "Typography",
      "design_deficiency": "Improper Text Styling",
      "response": false,
      "has_strong_agreement": true,
      "bounding_boxes": []
    },
    {
      "design_deficiency_category": "Typography",
      "design_deficiency": "Improper Line/Character Spacing",
      "response": false,
      "has_strong_agreement": true,
      "bounding_boxes": []
    },
    {
      "design_deficiency_category": "Typography",
      "design_deficiency": "Poor Text Hierarchy",
      "response": false,
      "has_strong_agreement": false
    },
    {
      "design_deficiency_category": "Color",
      "design_deficiency": "Insufficient Color Contrast for Readability",
      "response": false,
      "has_strong_agreement": true,
      "bounding_boxes": []
    },
    {
      "design_deficiency_category": "Color",
      "design_deficiency": "Excessive or Inconsistent Color Usage",
      "response": false,
      "has_strong_agreement": false
    },
    {
      "design_deficiency_category": "Color",
      "design_deficiency": "Inappropriate or Mismatched Color Combinations",
      "response": false,
      "has_strong_agreement": true
    },
    {
      "design_deficiency_category": "Imagery & Visualizations",
      "design_deficiency": "Irrelevant Visual Content",
      "response": false,
      "has_strong_agreement": true
    },
    {
      "design_deficiency_category": "Imagery & Visualizations",
      "design_deficiency": "Poor Image Quality/Editing",
      "response": false,
      "has_strong_agreement": true,
      "bounding_boxes": []
    },
    {
      "design_deficiency_category": "Imagery & Visualizations",
      "design_deficiency": "Improper Image Sizing",
      "response": false,
      "has_strong_agreement": true,
      "bounding_boxes": []
    },
    {
      "design_deficiency_category": "Imagery & Visualizations",
      "design_deficiency": "Inconsistent Visual Style Usage",
      "response": false,
      "has_strong_agreement": true
    }
  ],
  "image_dimensions": {
    "width": 1600,
    "height": 1200
  }
}