{
  "slide_id": 1476,
  "annotations": [
    {
      "design_deficiency_category": "Composition & Layout",
      "design_deficiency": "Poor Visual Hierarchy",
      "response": true,
      "has_strong_agreement": false
    },
    {
      "design_deficiency_category": "Composition & Layout",
      "design_deficiency": "Cluttered Layout",
      "response": true,
      "has_strong_agreement": true
    },
    {
      "design_deficiency_category": "Composition & Layout",
      "design_deficiency": "Unbalanced Space Distribution",
      "response": false,
      "has_strong_agreement": false
    },
    {
      "design_deficiency_category": "Composition & Layout",
      "design_deficiency": "Content Alignment Issues",
      "response": false,
      "has_strong_agreement": false,
      "bounding_boxes": []
    },
    {
      "design_deficiency_category": "Composition & Layout",
      "design_deficiency": "Content Overflow/Cut-off",
      "response": true,
      "has_strong_agreement": false,
      "bounding_boxes": [
        {
          "x": 55.39935325928466,
          "y": 694.2219200455479,
          "width": 1280.3937660548754,
          "height": 185.60753458524835
        }
      ]
    },
    {
      "design_deficiency_category": "Composition & Layout",
      "design_deficiency": "Occluded Content",
      "response": false,
      "has_strong_agreement": false,
      "bounding_boxes": []
    },
    {
      "design_deficiency_category": "Typography",
      "design_deficiency": "Illegible Typeface Selection or Usage",
      "response": false,
      "has_strong_agreement": true,
      "bounding_boxes": []
    },
    {
      "design_deficiency_category": "Typography",
      "design_deficiency": "Improper Font Sizing",
      "response": true,
      "has_strong_agreement": false,
      "bounding_boxes": [
        {
          "x": 110.82879612825167,
          "y": 454.7489413188143,
          "width": 1386.0859044162128,
          "height": 309.739866908651
        },
        {
          "x": 464.2645894784886,
          "y": 341.8366007605111,
          "width": 866.1487240959451,
          "height": 91.61772470833341
        }
      ]
    },
    {
      "design_deficiency_category": "Typography",
      "design_deficiency": "Excessive Text Volume",
      "response": false,
      "has_strong_agreement": false
    },
    {
      "design_deficiency_category": "Typography",
      "design_deficiency": "Improper Text Styling",
      "response": true,
      "has_strong_agreement": false,
      "bounding_boxes": [
        {
          "x": 141.80278281911674,
          "y": 164.367816091954,
          "width": 1277.676950998185,
          "height": 180.03629764065334
        },
        {
          "x": 153.41802782819116,
          "y": 466.36418632788866,
          "width": 1322.2020568663038,
          "height": 315.54748941318815
        },
        {
          "x": 117.26711926613788,
          "y": 347.21652929921396,
          "width": 400.7955276096144,
          "height": 75.3189995418399
        }
      ]
    },
    {
      "design_deficiency_category": "Typography",
      "design_deficiency": "Improper Line/Character Spacing",
      "response": false,
      "has_strong_agreement": true,
      "bounding_boxes": []
    },
    {
      "design_deficiency_category": "Typography",
      "design_deficiency": "Poor Text Hierarchy",
      "response": true,
      "has_strong_agreement": false
    },
    {
      "design_deficiency_category": "Color",
      "design_deficiency": "Insufficient Color Contrast for Readability",
      "response": false,
      "has_strong_agreement": true,
      "bounding_boxes": []
    },
    {
      "design_deficiency_category": "Color",
      "design_deficiency": "Excessive or Inconsistent Color Usage",
      "response": true,
      "has_strong_agreement": false
    },
    {
      "design_deficiency_category": "Color",
      "design_deficiency": "Inappropriate or Mismatched Color Combinations",
      "response": false,
      "has_strong_agreement": false
    },
    {
      "design_deficiency_category": "Imagery & Visualizations",
      "design_deficiency": "Irrelevant Visual Content",
      "response": true,
      "has_strong_agreement": false
    },
    {
      "design_deficiency_category": "Imagery & Visualizations",
      "design_deficiency": "Poor Image Quality/Editing",
      "response": false,
      "has_strong_agreement": true,
      "bounding_boxes": []
    },
    {
      "design_deficiency_category": "Imagery & Visualizations",
      "design_deficiency": "Improper Image Sizing",
      "response": false,
      "has_strong_agreement": true,
      "bounding_boxes": []
    },
    {
      "design_deficiency_category": "Imagery & Visualizations",
      "design_deficiency": "Inconsistent Visual Style Usage",
      "response": false,
      "has_strong_agreement": false
    }
  ],
  "image_dimensions": {
    "width": 1600,
    "height": 900
  }
}